yuxin_auth/__init__.py
yuxin_auth-2025.7.25.2.dist-info/METADATA
yuxin_auth-2025.7.25.2.dist-info/WHEEL
yuxin_auth-2025.7.25.2.dist-info/licenses/LICENSE
yuxin_auth-2025.7.25.2.dist-info/RECORD
