Metadata-Version: 2.4
Name: yuxin-auth
Version: 2025.7.25.2
Summary: 使用requests登录宇信系统
License-File: LICENSE
Requires-Python: >=3.12
Requires-Dist: ddddocr>=1.5.6
Requires-Dist: requests>=2.32.4
